{
  "schema_version": "projects.v1",
  "curated": [
    {
      "id": "AOC2024",
      "name": "AOC2024",
      "show": true,
      "summary": "Advent of Code 2024 solutions, exploring puzzle-solving approaches in Go.",
      "repo": "https://github.com/MrCodeEU/AOC2024",
      "homepage": null,
      "featured": false,
      "topics": [
        "Go",
        "Algorithms",
        "Puzzles"
      ],
      "images": [
        "https://picsum.photos/seed/aoc2024/800/450"
      ],
      "links": [],
      "order": 100
    },
    {
      "id": "AdventOfCode2022_MrCode",
      "name": "AdventOfCode2022_MrCode",
      "show": false,
      "summary": "",
      "repo": "https://github.com/MrCodeEU/AdventOfCode2022_MrCode",
      "homepage": null,
      "featured": false,
      "topics": [],
      "images": []
    },
    {
      "id": "Flexbar-Plugin-Youtube-Music-Desktop-App",
      "name": "Flexbar-Plugin-Youtube-Music-Desktop-App",
      "show": true,
      "summary": "Flexbar plugin integrating YouTube Music Desktop App playback controls.",
      "repo": "https://github.com/MrCodeEU/Flexbar-Plugin-Youtube-Music-Desktop-App",
      "homepage": null,
      "featured": false,
      "topics": [
        "TypeScript",
        "Plugin",
        "Desktop"
      ],
      "images": [
        "/assets/portfolio/Flexbar-Plugin-Youtube-Music-Desktop-App/0.webp",
        "/assets/portfolio/Flexbar-Plugin-Youtube-Music-Desktop-App/1.webp"
      ],
      "links": [],
      "order": 110
    },
    {
      "id": "Game-of-Life-Multiplatform",
      "name": "Game-of-Life-Multiplatform",
      "show": true,
      "summary": "Conway's Game of Life implemented with Kotlin Multiplatform for desktop and mobile.",
      "repo": "https://github.com/MrCodeEU/Game-of-Life-Multiplatform",
      "homepage": null,
      "featured": false,
      "topics": [
        "Kotlin",
        "Multiplatform",
        "Simulation"
      ],
      "images": [
        "/assets/portfolio/Game-of-Life-Multiplatform/0.webp"
      ],
      "links": [],
      "order": 70
    },
    {
      "id": "ImageNameConverter",
      "name": "ImageNameConverter",
      "show": false,
      "summary": "",
      "repo": "https://github.com/MrCodeEU/ImageNameConverter",
      "homepage": null,
      "featured": false,
      "topics": [],
      "images": []
    },
    {
      "id": "LSTM-Based-Speaker-Diarization",
      "name": "LSTM-Based-Speaker-Diarization",
      "show": true,
      "summary": "LSTM-based neural network for speaker diarization on audio recordings.",
      "repo": "https://github.com/MrCodeEU/LSTM-Based-Speaker-Diarization",
      "homepage": null,
      "featured": false,
      "topics": [
        "Python",
        "PyTorch",
        "Machine Learning",
        "Audio"
      ],
      "images": [
        "/assets/portfolio/LSTM-Based-Speaker-Diarization/0.webp",
        "/assets/portfolio/LSTM-Based-Speaker-Diarization/1.webp"
      ],
      "order": 40
    },
    {
      "id": "Lebenslauf",
      "name": "Lebenslauf",
      "show": true,
      "summary": "Source for my CV/resume, built as a small static web project.",
      "repo": "https://github.com/MrCodeEU/Lebenslauf",
      "homepage": null,
      "featured": false,
      "topics": [
        "Web",
        "CSS",
        "Resume"
      ],
      "images": [
        "/assets/portfolio/Lebenslauf/0.webp",
        "/assets/portfolio/Lebenslauf/1.webp"
      ],
      "order": 80
    },
    {
      "id": "MMS-Projekt-Spielesammlung",
      "name": "MMS-Projekt-Spielesammlung",
      "show": false,
      "summary": "",
      "repo": "https://github.com/MrCodeEU/MMS-Projekt-Spielesammlung",
      "homepage": null,
      "featured": false,
      "topics": [],
      "images": []
    },
    {
      "id": "MrCodeCSS",
      "name": "MrCodeCSS",
      "show": false,
      "summary": "",
      "repo": "https://github.com/MrCodeEU/MrCodeCSS",
      "homepage": null,
      "featured": false,
      "topics": [],
      "images": []
    },
    {
      "id": "MrCodeEU",
      "name": "MrCodeEU",
      "show": false,
      "summary": "",
      "repo": "https://github.com/MrCodeEU/MrCodeEU",
      "homepage": null,
      "featured": false,
      "topics": [],
      "images": []
    },
    {
      "id": "WordWiz",
      "name": "WordWiz",
      "show": true,
      "summary": "Word-game helper and solver built as a web app.",
      "repo": "https://github.com/MrCodeEU/WordWiz",
      "homepage": null,
      "featured": false,
      "topics": [
        "TypeScript",
        "Web",
        "Game"
      ],
      "images": [
        "/assets/portfolio/WordWiz/0.webp",
        "/assets/portfolio/WordWiz/1.webp"
      ],
      "links": [
        {
          "name": "Live",
          "url": "https://wordwiz.mljr.eu/"
        }
      ],
      "order": 120
    },
    {
      "id": "cg-lab-2023-project-reineggersilber",
      "name": "cg-lab-2023-project-reineggersilber",
      "show": true,
      "summary": "Computer graphics lab project: real-time 3D rendering exercises.",
      "repo": "https://github.com/MrCodeEU/cg-lab-2023-project-reineggersilber",
      "homepage": null,
      "featured": false,
      "topics": [
        "C++",
        "OpenGL",
        "Computer Graphics"
      ],
      "images": [
        "/assets/portfolio/cg-lab-2023-project-reineggersilber/0.webp",
        "/assets/portfolio/cg-lab-2023-project-reineggersilber/1.webp"
      ],
      "order": 50
    },
    {
      "id": "cosmic-nightscout",
      "name": "cosmic-nightscout",
      "show": true,
      "summary": "Rust desktop applet for the COSMIC desktop showing live Nightscout glucose data.",
      "repo": "https://github.com/MrCodeEU/cosmic-nightscout",
      "homepage": null,
      "featured": true,
      "topics": [
        "Rust",
        "COSMIC",
        "Nightscout",
        "Linux"
      ],
      "images": [
        "https://picsum.photos/seed/cosmic-nightscout/800/450"
      ],
      "links": [],
      "order": 130
    },
    {
      "id": "face-auth",
      "name": "face-auth",
      "show": true,
      "summary": "Facial-recognition authentication PAM module written in Go.",
      "repo": "https://github.com/MrCodeEU/face-auth",
      "homepage": null,
      "featured": true,
      "topics": [
        "Rust",
        "PAM",
        "Security",
        "Linux"
      ],
      "images": [
        "https://picsum.photos/seed/face-auth-1/800/450",
        "https://picsum.photos/seed/face-auth-2/800/450",
        "https://picsum.photos/seed/face-auth-3/800/450"
      ],
      "links": [],
      "order": 140
    },
    {
      "id": "godrive",
      "name": "goDrive",
      "show": true,
      "summary": "Self-hosted file sync and sharing app with mobile clients, demo mode, and WebDAV support.",
      "repo": "https://github.com/MrCodeEU/goDrive",
      "homepage": null,
      "featured": true,
      "topics": [
        "Go",
        "Flutter",
        "SQLite",
        "Sync"
      ],
      "images": [
        "https://picsum.photos/seed/godrive-1/800/450",
        "https://picsum.photos/seed/godrive-2/800/450",
        "https://picsum.photos/seed/godrive-3/800/450"
      ],
      "links": [
        {
          "name": "Demo",
          "url": "https://godrive-demo.mljr.eu"
        }
      ],
      "order": 150
    },
    {
      "id": "homelab-automation",
      "name": "homelab-automation",
      "show": true,
      "summary": "Ansible-driven configuration for a self-hosted homelab: reverse proxy, monitoring, and services.",
      "repo": "https://github.com/MrCodeEU/homelab-automation",
      "homepage": null,
      "featured": false,
      "topics": [
        "Ansible",
        "Docker",
        "Homelab",
        "Monitoring"
      ],
      "images": [
        "https://picsum.photos/seed/homelab-automation/800/450"
      ],
      "links": [],
      "order": 30
    },
    {
      "id": "homelab-speedtest",
      "name": "homelab-speedtest",
      "show": true,
      "summary": "Go and Svelte network performance monitoring for a self-hosted homelab.",
      "repo": "https://github.com/MrCodeEU/homelab-speedtest",
      "homepage": null,
      "featured": true,
      "topics": [
        "Go",
        "Svelte",
        "Monitoring",
        "Docker"
      ],
      "images": [
        "/assets/portfolio/homelab-speedtest/0.webp",
        "/assets/portfolio/homelab-speedtest/1.webp"
      ],
      "links": [],
      "order": 160
    },
    {
      "id": "homepage",
      "name": "homepage",
      "show": false,
      "summary": "",
      "repo": "https://github.com/MrCodeEU/homepage",
      "homepage": null,
      "featured": false,
      "topics": [],
      "images": []
    },
    {
      "id": "jku-master-project-network-devices-power-consumption-analysis",
      "name": "jku-master-project-network-devices-power-consumption-analysis",
      "show": true,
      "summary": "Master's project analyzing power consumption of network devices.",
      "repo": "https://github.com/MrCodeEU/jku-master-project-network-devices-power-consumption-analysis",
      "homepage": null,
      "featured": false,
      "topics": [
        "Python",
        "Networking",
        "Data Analysis"
      ],
      "images": [
        "/assets/portfolio/jku-master-project-network-devices-power-consumption-analysis/0.webp",
        "/assets/portfolio/jku-master-project-network-devices-power-consumption-analysis/1.webp"
      ],
      "order": 60
    },
    {
      "id": "mljr-comps",
      "name": "mljr-comps",
      "show": false,
      "summary": "Neo-brutalist Go/gomponents UI component library powering mljr.eu.",
      "repo": "https://github.com/MrCodeEU/mljr-comps",
      "homepage": null,
      "featured": true,
      "topics": [
        "Go",
        "gomponents",
        "UI",
        "CSS"
      ],
      "images": [
        "https://picsum.photos/seed/mljr-comps/800/450"
      ],
      "links": [
        {
          "name": "Component showcase",
          "url": "https://comps.mljr.eu"
        }
      ]
    },
    {
      "id": "mljr-data",
      "name": "mljr-data",
      "show": false,
      "summary": "",
      "repo": "https://github.com/MrCodeEU/mljr-data",
      "homepage": null,
      "featured": false,
      "topics": [],
      "images": []
    },
    {
      "id": "mljr-web",
      "name": "mljr-web",
      "show": true,
      "summary": "Personal portfolio monorepo — Go/gomponents, Datastar, Tailwind v4, neo-brutalist 4-theme component library.",
      "repo": "https://github.com/MrCodeEU/mljr-web",
      "homepage": "https://mljr.eu",
      "featured": true,
      "topics": [
        "Go",
        "gomponents",
        "Datastar",
        "Tailwind",
        "UI"
      ],
      "images": [
        "/assets/portfolio/mljrCSS/0.webp"
      ],
      "links": [
        {
          "name": "Component showcase",
          "url": "https://ui.mljr.eu"
        }
      ],
      "order": 170
    },
    {
      "id": "mljrCSS",
      "name": "mljrCSS",
      "show": false,
      "summary": "",
      "repo": "https://github.com/MrCodeEU/mljrCSS",
      "homepage": null,
      "featured": false,
      "topics": [],
      "images": []
    },
    {
      "id": "nightscout-display",
      "name": "nightscout-display",
      "show": true,
      "summary": "E-ink/embedded display client for Nightscout CGM data.",
      "repo": "https://github.com/MrCodeEU/nightscout-display",
      "homepage": null,
      "featured": false,
      "topics": [
        "Go",
        "Nightscout",
        "Embedded"
      ],
      "images": [
        "/assets/portfolio/nightscout-display/0.webp",
        "/assets/portfolio/nightscout-display/1.webp"
      ],
      "links": [],
      "order": 180
    },
    {
      "id": "nightscout-librelink-up-go",
      "name": "nightscout-librelink-up-go",
      "show": true,
      "summary": "Go bridge syncing LibreLink Up glucose readings into Nightscout.",
      "repo": "https://github.com/MrCodeEU/nightscout-librelink-up-go",
      "homepage": null,
      "featured": false,
      "topics": [
        "Go",
        "Nightscout",
        "LibreLink"
      ],
      "images": [
        "/assets/portfolio/nightscout-librelink-up-go/0.webp",
        "/assets/portfolio/nightscout-librelink-up-go/1.webp"
      ],
      "links": [],
      "order": 190
    },
    {
      "id": "nightscout-tray",
      "name": "nightscout-tray",
      "show": true,
      "summary": "Cross-platform system tray app showing current Nightscout glucose at a glance.",
      "repo": "https://github.com/MrCodeEU/nightscout-tray",
      "homepage": null,
      "featured": false,
      "topics": [
        "Go",
        "Nightscout",
        "Desktop"
      ],
      "images": [
        "/assets/portfolio/nightscout-tray/0.webp",
        "/assets/portfolio/nightscout-tray/1.webp"
      ],
      "links": [],
      "order": 200
    },
    {
      "id": "service-template",
      "name": "service-template",
      "show": true,
      "summary": "Reusable Go service scaffold with CI, Docker, and homelab deployment conventions baked in.",
      "repo": "https://github.com/MrCodeEU/service-template",
      "homepage": null,
      "featured": false,
      "topics": [
        "Go",
        "Template",
        "CI/CD",
        "Docker"
      ],
      "images": [
        "/assets/portfolio/service-template/0.webp",
        "/assets/portfolio/service-template/1.webp"
      ],
      "links": [
        {
          "name": "Prod",
          "url": "https://template.mljr.eu"
        },
        {
          "name": "Staging",
          "url": "https://template.dev.mljr.eu"
        }
      ],
      "order": 20
    },
    {
      "id": "sudoku-gen",
      "name": "sudoku-gen",
      "show": true,
      "summary": "Sudoku puzzle generator and solver written in Go.",
      "repo": "https://github.com/MrCodeEU/sudoku-gen",
      "homepage": null,
      "featured": false,
      "topics": [
        "Go",
        "Algorithms",
        "CLI"
      ],
      "images": [
        "/assets/portfolio/sudoku-gen/0.webp",
        "/assets/portfolio/sudoku-gen/1.webp",
        "/assets/portfolio/sudoku-gen/2.webp",
        "/assets/portfolio/sudoku-gen/3.webp"
      ],
      "links": [],
      "order": 10
    },
    {
      "id": "sudoku_gen_go",
      "name": "sudoku_gen_go",
      "show": false,
      "summary": "",
      "repo": "https://github.com/MrCodeEU/sudoku_gen_go",
      "homepage": null,
      "featured": false,
      "topics": [],
      "images": []
    },
    {
      "id": "webcambot",
      "name": "webcambot",
      "show": false,
      "summary": "",
      "repo": "https://github.com/MrCodeEU/webcambot",
      "homepage": null,
      "featured": false,
      "topics": [],
      "images": []
    },
    {
      "id": "zepp2hass-watch",
      "name": "zepp2hass-watch",
      "show": true,
      "summary": "Zepp OS watch app bridging smartwatch sensor data into Home Assistant.",
      "repo": "https://github.com/MrCodeEU/zepp2hass-watch",
      "homepage": null,
      "featured": false,
      "topics": [
        "Zepp OS",
        "Home Assistant",
        "Wearables"
      ],
      "images": [
        "https://picsum.photos/seed/zepp2hass-watch/800/450"
      ],
      "links": [],
      "order": 210
    }
  ]
}
